paegents/__init__.py
paegents/agent_payments.py
paegents/x402_signing.py
paegents-2.5.0.dist-info/licenses/LICENSE
paegents-2.5.0.dist-info/METADATA
paegents-2.5.0.dist-info/WHEEL
paegents-2.5.0.dist-info/top_level.txt
paegents-2.5.0.dist-info/RECORD
