Metadata-Version: 2.4
Name: paegents
Version: 2.5.0
Summary: Official Python SDK for Paegents - Payment infrastructure for AI agents with Service Catalog and Usage Escrow
Home-page: https://github.com/paegents/python-sdk
Author: Paegents Inc
Author-email: Paegents Inc <support@paegents.com>
License: MIT
Project-URL: Homepage, https://paegents.com
Project-URL: Documentation, https://docs.paegents.com
Project-URL: Repository, https://github.com/paegents/python-sdk
Project-URL: Bug Tracker, https://github.com/paegents/python-sdk/issues
Keywords: payments,ai,agents,fintech,automation,stripe,braintree,stablecoin
Classifier: Development Status :: 5 - Production/Stable
Classifier: Intended Audience :: Developers
Classifier: Topic :: Software Development :: Libraries :: Python Modules
Classifier: Topic :: Office/Business :: Financial
Classifier: Topic :: Internet :: WWW/HTTP :: Dynamic Content
Classifier: License :: OSI Approved :: MIT License
Classifier: Programming Language :: Python :: 3
Classifier: Programming Language :: Python :: 3.7
Classifier: Programming Language :: Python :: 3.8
Classifier: Programming Language :: Python :: 3.9
Classifier: Programming Language :: Python :: 3.10
Classifier: Programming Language :: Python :: 3.11
Classifier: Operating System :: OS Independent
Requires-Python: >=3.7
License-File: LICENSE
Requires-Dist: requests>=2.25.0
Requires-Dist: eth-account>=0.8.0
Requires-Dist: x402>=0.1.0
Provides-Extra: dev
Requires-Dist: pytest>=6.0; extra == "dev"
Requires-Dist: pytest-cov>=2.0; extra == "dev"
Requires-Dist: black>=21.0.0; extra == "dev"
Requires-Dist: flake8>=3.8.0; extra == "dev"
Requires-Dist: mypy>=0.800; extra == "dev"
Requires-Dist: isort>=5.0.0; extra == "dev"
Dynamic: author
Dynamic: home-page
Dynamic: license-file
Dynamic: requires-python
